ichor/files/__init__.py
ichor/files/pdb_file.py
ichor/files/xyz.py
ichor-1.0.0.dist-info/LICENSE
ichor-1.0.0.dist-info/METADATA
ichor-1.0.0.dist-info/WHEEL
ichor-1.0.0.dist-info/top_level.txt
ichor-1.0.0.dist-info/RECORD
