Metadata-Version: 2.1
Name: ichor
Version: 1.0.0
Summary: File Reading for different CC inputs files.
Author: Y. Manchev
License: MIT License
Project-URL: Homepage, https://github.com/m-julian/ichor
Keywords: computational
Classifier: License :: OSI Approved :: MIT License
Classifier: Programming Language :: Python
Classifier: Programming Language :: Python :: 3
Requires-Python: >=3.8
License-File: LICENSE
